backtrader_next/__init__.py
backtrader_next/analyzer.py
backtrader_next/broker.py
backtrader_next/cerebro.py
backtrader_next/comminfo.py
backtrader_next/dataseries.py
backtrader_next/errors.py
backtrader_next/feed.py
backtrader_next/fillers.py
backtrader_next/flt.py
backtrader_next/functions.py
backtrader_next/indicator.py
backtrader_next/linebuffer.py
backtrader_next/lineiterator.py
backtrader_next/lineroot.py
backtrader_next/lineseries.py
backtrader_next/mathsupport.py
backtrader_next/metabase.py
backtrader_next/observer.py
backtrader_next/order.py
backtrader_next/position.py
backtrader_next/resamplerfilter.py
backtrader_next/signal.py
backtrader_next/sizer.py
backtrader_next/store.py
backtrader_next/strategy.py
backtrader_next/talib.py
backtrader_next/timer.py
backtrader_next/trade.py
backtrader_next/tradingcal.py
backtrader_next/version.py
backtrader_next/writer.py
backtrader_next/analyzers/__init__.py
backtrader_next/analyzers/annualreturn.py
backtrader_next/analyzers/calmar.py
backtrader_next/analyzers/drawdown.py
backtrader_next/analyzers/eq.py
backtrader_next/analyzers/leverage.py
backtrader_next/analyzers/logreturnsrolling.py
backtrader_next/analyzers/periodstats.py
backtrader_next/analyzers/positions.py
backtrader_next/analyzers/pyfolio.py
backtrader_next/analyzers/returns.py
backtrader_next/analyzers/sharpe.py
backtrader_next/analyzers/sqn.py
backtrader_next/analyzers/timereturn.py
backtrader_next/analyzers/tradeanalyzer.py
backtrader_next/analyzers/transactions.py
backtrader_next/analyzers/vwr.py
backtrader_next/brokers/__init__.py
backtrader_next/brokers/bbroker.py
backtrader_next/brokers/ibbroker.py
backtrader_next/brokers/oandabroker.py
backtrader_next/brokers/vcbroker.py
backtrader_next/btrun/__init__.py
backtrader_next/btrun/btrun.py
backtrader_next/commissions/__init__.py
backtrader_next/feeds/__init__.py
backtrader_next/feeds/blaze.py
backtrader_next/feeds/btcsv.py
backtrader_next/feeds/chainer.py
backtrader_next/feeds/csvgeneric.py
backtrader_next-2.3.2.dist-info/METADATA
backtrader_next-2.3.2.dist-info/WHEEL
backtrader_next-2.3.2.dist-info/licenses/LICENSE
backtrader_next-2.3.2.dist-info/RECORD
