Metadata-Version: 2.4
Name: backtrader_next
Version: 2.3.2
Summary: Live Trading and backtesting platform in Python
Project-URL: Homepage, https://github.com/smalinin/backtrader_next
Project-URL: Source, https://github.com/smalinin/backtrader_next
Author: smalinin
License: GPL-3.0-or-later
License-File: LICENSE
Classifier: Development Status :: 3 - Alpha
Classifier: License :: OSI Approved :: GNU General Public License v3 or later (GPLv3+)
Classifier: Operating System :: OS Independent
Classifier: Programming Language :: Python :: 3
Requires-Python: >=3.11
Requires-Dist: bn-lightweight-charts>=1.1.0
Requires-Dist: numba>=0.61.2
Requires-Dist: numpy<2.3,>=2.0
Requires-Dist: pandas>=2.2.3
Requires-Dist: plotly>=6.1.2
Requires-Dist: tqdm
